LICENSE
MANIFEST.in
README.rst
setup.py
fcxref/__init__.py
fcxref/_version.py
fcxref/cli.py
fcxref/group_references_by_document_path.py
fcxref/root_by_document_path.py
fcxref.egg-info/PKG-INFO
fcxref.egg-info/SOURCES.txt
fcxref.egg-info/dependency_links.txt
fcxref.egg-info/entry_points.txt
fcxref.egg-info/top_level.txt
fcxref/find/__init__.py
fcxref/find/extract_document.py
fcxref/find/find_references_in_root.py
fcxref/find/make_find.py
fcxref/find/match.py
fcxref/find/query.py
fcxref/find/reference.py
fcxref/find/xml_property.py
fcxref/find/xml_property_name.py
fcxref/remove/__init__.py
fcxref/remove/remove.py
fcxref/remove/remove_document_from_xlinks.py
fcxref/rename/__init__.py
fcxref/rename/label.py
fcxref/rename/make_rename.py
fcxref/rename/rename_owner_document.py
fcxref/rename/rename_references_in_root.py