Metadata-Version: 2.1
Name: fcxref
Version: 0.4.0
Summary: Manages FreeCAD external references.
Home-page: https://github.com/gbroques/fcxref
Author: G Roques
License: GNU Lesser General Public License v2 or later (LGPLv2+)
Classifier: License :: OSI Approved :: GNU Lesser General Public License v2 or later (LGPLv2+)
Classifier: Programming Language :: Python :: 3 :: Only
License-File: LICENSE
